ree_scylla/__init__.py
ree_scylla/cql.py
ree_scylla-0.0.2.dist-info/METADATA
ree_scylla-0.0.2.dist-info/WHEEL
ree_scylla-0.0.2.dist-info/top_level.txt
ree_scylla-0.0.2.dist-info/RECORD
